README
setup.cfg
setup.py
convoy/__init__.py
convoy/combo.py
convoy/meta.py
convoy.egg-info/PKG-INFO
convoy.egg-info/SOURCES.txt
convoy.egg-info/dependency_links.txt
convoy.egg-info/top_level.txt