Metadata-Version: 1.1
Name: convoy
Version: 0.4.4
Summary: A combo-loader for Javascript and CSS.
Home-page: https://launchpad.net/convoy
Author: Canonical Javascripters
Author-email: -
License: AGPL
Platform: UNKNOWN
Classifier: Development Status :: 5 - Production/Stable
Classifier: Environment :: Web Environment
Classifier: Intended Audience :: Developers
Classifier: Intended Audience :: Information Technology
Classifier: License :: OSI Approved :: GNU Affero General Public License v3
Classifier: Programming Language :: Python
Classifier: Programming Language :: Python :: 2
Classifier: Programming Language :: Python :: 3
Classifier: Topic :: Internet :: WWW/HTTP
